gift/__init__.py
gift/__main__.py
gift/cli.py
gift/core.py
gift_stego-1.0.0.dist-info/licenses/LICENSE
tests/__init__.py
tests/test_crypto.py
gift_stego-1.0.0.dist-info/METADATA
gift_stego-1.0.0.dist-info/WHEEL
gift_stego-1.0.0.dist-info/entry_points.txt
gift_stego-1.0.0.dist-info/top_level.txt
gift_stego-1.0.0.dist-info/RECORD
