Metadata-Version: 2.4
Name: gift-stego
Version: 1.0.0
Summary: GIF Analysis Steganography Library - Hide and recover data in GIF files using LSB steganography
Home-page: https://github.com/dtmsecurity/gift-stego
Author: dtm
Author-email: dtm <dtmsecurity@gmail.com>
License: MIT
Project-URL: Homepage, https://github.com/dtmsecurity/gift-stego
Project-URL: Repository, https://github.com/dtmsecurity/gift-stego
Project-URL: Issues, https://github.com/dtmsecurity/gift-stego/issues
Project-URL: Documentation, https://dtm.uk/gif-steganography/
Keywords: steganography,gif,security,cryptography,privacy,lsb,watermarking,data-hiding
Classifier: Development Status :: 4 - Beta
Classifier: Intended Audience :: Developers
Classifier: Intended Audience :: Information Technology
Classifier: Intended Audience :: Science/Research
Classifier: Topic :: Security
Classifier: Topic :: Security :: Cryptography
Classifier: Topic :: Multimedia :: Graphics
Classifier: License :: OSI Approved :: MIT License
Classifier: Programming Language :: Python :: 3
Classifier: Programming Language :: Python :: 3.7
Classifier: Programming Language :: Python :: 3.8
Classifier: Programming Language :: Python :: 3.9
Classifier: Programming Language :: Python :: 3.10
Classifier: Programming Language :: Python :: 3.11
Classifier: Programming Language :: Python :: 3.12
Classifier: Operating System :: OS Independent
Requires-Python: >=3.7
License-File: LICENSE
Provides-Extra: dev
Requires-Dist: pytest>=7.0; extra == "dev"
Requires-Dist: pytest-cov>=3.0; extra == "dev"
Requires-Dist: black>=22.0; extra == "dev"
Requires-Dist: mypy>=0.950; extra == "dev"
Requires-Dist: flake8>=4.0; extra == "dev"
Dynamic: author
Dynamic: home-page
Dynamic: license-file
Dynamic: requires-python
